planobs/__init__.py
planobs/api.py
planobs/credentials.py
planobs/data/references/1241_references.csv
planobs/data/references/1243_references.csv
planobs/data/references/1244_references.csv
planobs/data/references/1245_references.csv
planobs/data/references/1246_references.csv
planobs/data/references/1247_references.csv
planobs/data/references/1248_references.csv
planobs/data/references/1249_references.csv
planobs/data/references/1287_references.csv
planobs/data/references/1288_references.csv
planobs/data/references/1289_references.csv
planobs/data/references/1290_references.csv
planobs/data/references/1291_references.csv
planobs/data/references/1292_references.csv
planobs/data/references/1293_references.csv
planobs/data/references/1294_references.csv
planobs/data/references/1295_references.csv
planobs/data/references/1296_references.csv
planobs/data/references/1297_references.csv
planobs/data/references/1298_references.csv
planobs/data/references/1299_references.csv
planobs/data/references/1300_references.csv
planobs/data/references/1301_references.csv
planobs/data/references/1302_references.csv
planobs/data/references/1333_references.csv
planobs/data/references/1334_references.csv
planobs/data/references/1335_references.csv
planobs/data/references/1336_references.csv
planobs/data/references/1337_references.csv
planobs/data/references/1338_references.csv
planobs/data/references/1339_references.csv
planobs/data/references/1340_references.csv
planobs/data/references/1341_references.csv
planobs/data/references/1342_references.csv
planobs/data/references/1343_references.csv
planobs/data/references/1344_references.csv
planobs/data/references/1345_references.csv
planobs/data/references/1346_references.csv
planobs/data/references/1347_references.csv
planobs/data/references/1348_references.csv
planobs/data/references/1349_references.csv
planobs/data/references/1350_references.csv
planobs/data/references/1351_references.csv
planobs/data/references/1352_references.csv
planobs-0.7.3.dist-info/LICENSE
planobs-0.7.3.dist-info/METADATA
planobs-0.7.3.dist-info/WHEEL
planobs-0.7.3.dist-info/RECORD
