Metadata-Version: 2.1
Name: planobs
Version: 0.7.3
Summary: Plan observations with the Zwicky Transient Facility
Home-page: https://github.com/simeonreusch/planobs
License: BSD-3-Clause
Keywords: astroparticle physics,science,multimessenger astronomy,ZTF
Author: Simeon Reusch
Author-email: simeon.reusch@desy.de
Maintainer: Simeon Reusch
Maintainer-email: simeon.reusch@desy.de
Requires-Python: >=3.10,<4
Classifier: License :: OSI Approved :: BSD License
Classifier: Operating System :: OS Independent
Classifier: Programming Language :: Python :: 3
Classifier: Programming Language :: Python :: 3.10
Classifier: Programming Language :: Python :: 3.11
Provides-Extra: slack
Requires-Dist: Flask (>=2.1.3,<3.0.0) ; extra == "slack"
Requires-Dist: Shapely (>=1.8.2)
Requires-Dist: astroplan (>=0.7)
Requires-Dist: astropy (>=5.0)
Requires-Dist: geopandas (>=0.11,<0.14)
Requires-Dist: gunicorn (>=20.1.0,<21.0.0) ; extra == "slack"
Requires-Dist: lxml (>=4.9)
Requires-Dist: matplotlib (>=3.2)
Requires-Dist: pandas (>=1.4.3)
Requires-Dist: penquins (>=2.2.0)
Requires-Dist: pydantic (>=1.0)
Requires-Dist: slackclient (>=2.9.4,<3.0.0) ; extra == "slack"
Requires-Dist: slackeventsapi (>=3.0.1,<4.0.0) ; extra == "slack"
Requires-Dist: tqdm (>=4.64.0)
Requires-Dist: ztfquery (>=1.18.4)
Project-URL: Repository, https://github.com/simeonreusch/planobs
